zc/recipe/cmmi/README.rst
zc/recipe/cmmi/__init__.py
zc/recipe/cmmi/downloadcache.rst
zc/recipe/cmmi/misc.rst
zc/recipe/cmmi/patching.rst
zc/recipe/cmmi/shared.rst
zc/recipe/cmmi/tests.py
zc_recipe_cmmi-5.0.dist-info/licenses/LICENSE.txt
zc_recipe_cmmi-5.0.dist-info/METADATA
zc_recipe_cmmi-5.0.dist-info/WHEEL
zc_recipe_cmmi-5.0.dist-info/entry_points.txt
zc_recipe_cmmi-5.0.dist-info/top_level.txt
zc_recipe_cmmi-5.0.dist-info/zip-safe
zc_recipe_cmmi-5.0.dist-info/RECORD
